ceODBC/__init__.py
ceODBC/constants.py
ceODBC/constructors.py
ceODBC/driver.cp310-win32.pyd
ceODBC/driver.cp310-win_amd64.pyd
ceODBC/driver.cp311-win32.pyd
ceODBC/driver.cp311-win_amd64.pyd
ceODBC/driver.cp37-win32.pyd
ceODBC/driver.cp37-win_amd64.pyd
ceODBC/driver.cp38-win32.pyd
ceODBC/driver.cp38-win_amd64.pyd
ceODBC/driver.cp39-win32.pyd
ceODBC/driver.cp39-win_amd64.pyd
ceODBC/exceptions.py
ceODBC/version.py
ceODBC-3.1.dist-info/METADATA
ceODBC-3.1.dist-info/WHEEL
ceODBC-3.1.dist-info/top_level.txt
ceODBC-3.1.dist-info/RECORD
