Metadata-Version: 2.1
Name: ceODBC
Version: 3.1
Summary: Python interface to ODBC
Author-email: Anthony Tuininga <anthony.tuininga@gmail.com>
License: BSD License
Project-URL: Homepage, https://anthony-tuininga.github.io/ceODBC
Classifier: Development Status :: 5 - Production/Stable
Classifier: Intended Audience :: Developers
Classifier: License :: OSI Approved :: BSD License
Classifier: Natural Language :: English
Classifier: Operating System :: OS Independent
Classifier: Programming Language :: Cython
Classifier: Programming Language :: Python
Classifier: Topic :: Database
Requires-Python: >=3.7
